canonical_args/__init__.py
canonical_args/check.py
canonical_args/function.py
canonical_args/structure.py
canonical_args-0.4.1.dist-info/LICENSE.txt
canonical_args-0.4.1.dist-info/METADATA
canonical_args-0.4.1.dist-info/RECORD
canonical_args-0.4.1.dist-info/WHEEL
canonical_args-0.4.1.dist-info/top_level.txt
