Metadata-Version: 2.1
Name: canonical-args
Version: 0.4.1
Summary: A module for dynamically registering, checking, and working with nested argument specs.
Home-page: https://github.com/shonteag/canonical_args
Author: Shonte Amato-Grill
Author-email: shonte.amatogrill@gmail.com
Maintainer: Shonte Amato-Grill
Maintainer-email: shonte.amatogrill@gmail.com
License: UNKNOWN
Platform: UNKNOWN
Classifier: Programming Language :: Python :: 2.7
Classifier: Topic :: Software Development :: Libraries :: Python Modules
Classifier: Intended Audience :: Developers
